recursivX/__init__.py
recursivX/recursivX.py
recursivx-1.0.1.dist-info/licenses/LICENSE
recursivx-1.0.1.dist-info/METADATA
recursivx-1.0.1.dist-info/WHEEL
recursivx-1.0.1.dist-info/entry_points.txt
recursivx-1.0.1.dist-info/top_level.txt
recursivx-1.0.1.dist-info/RECORD
