Metadata-Version: 2.4
Name: recursivX
Version: 1.0.1
Summary: Recursive archive extractor with password detection
Home-page: https://github.com/Paul00/recursivX
Author: Paul Smith
Classifier: Programming Language :: Python :: 3
Classifier: License :: OSI Approved :: MIT License
Requires-Python: >=3.6
License-File: LICENSE
Dynamic: author
Dynamic: classifier
Dynamic: description
Dynamic: description-content-type
Dynamic: home-page
Dynamic: license-file
Dynamic: requires-python
Dynamic: summary
